docs/source/conf.py
example-scripts/calibration.py
example-scripts/efficiency.py
example-scripts/peak_fitting.py
example-scripts/resolution.py
gammaforge/__init__.py
gammaforge/characterisation.py
gammaforge/analysis/__init__.py
gammaforge/analysis/detector_analysis.py
gammaforge/analysis/fitting.py
gammaforge/utils/__init__.py
gammaforge/utils/file_handling.py
test/test_analysis.py
gammaforge-0.0.1.dist-info/LICENSE
gammaforge-0.0.1.dist-info/METADATA
gammaforge-0.0.1.dist-info/WHEEL
gammaforge-0.0.1.dist-info/top_level.txt
gammaforge-0.0.1.dist-info/RECORD
