Metadata-Version: 2.1
Name: gammaforge
Version: 0.0.1
Summary: A package to characterise gamma-ray space detectors.
Author-email: Jonathan Flunger <jonathan.flunger@gmail.com>
Project-URL: Homepage, https://github.com/jonathanflunger/gammaforge
Requires-Python: >=3.11
License-File: LICENSE
Requires-Dist: numpy >=1.26
Requires-Dist: scipy >=1.11
Requires-Dist: matplotlib >=3.7
Requires-Dist: pandas >=2.1
Requires-Dist: datetime >=4.0
